{
    "222": {
        "0": {
            "VIS": {
                "0": {
                    "GRAY": 1242
                },
                "1": {
                    "GRAY": 1250
                },
                "2": {
                    "GRAY": 1249
                },
                "3": {
                    "GRAY": 1245
                },
                "4": {
                    "GRAY": 1260
                },
                "5": {
                    "GRAY": 1176
                },
                "6": {
                    "GRAY": 1083
                },
                "7": {
                    "GRAY": 1005
                },
                "8": {
                    "GRAY": 929
                },
                "9": {
                    "GRAY": 1171
                }
            }
        }
    }
}